<manifest alg="2" build="2018.1.0.386" opt="true" iceEnabled="true" iceMarkupVersion="2" iceEnabledOptions="link,responsive,cachebuster,textStyling" exportTarget="other" domain="http://www.liuconsulting.net" resolutions="1x" timestamp="1542684273690">
  <folder name="css">
    <file name="site_global.css" crc="4271355408"/>
    <file name="master_a-master.css" crc="4195444906" ref="contact:index:business"/>
    <file name="contact.css" crc="4129723786" ref="contact"/>
    <file name="index.css" crc="278364069" ref="index"/>
    <file name="business.css" crc="212121914" ref="business"/>
  </folder>
  <folder name="scripts">
    <file name="jquery-1.8.3.min.js" crc="209076791" ref="index:business:contact"/>
    <file name="museutils.js" crc="340535759" ref="index:business:contact"/>
    <file name="whatinput.js" crc="86476730" ref="index:business:contact"/>
    <file name="museconfig.js" crc="310584261" ref="index:business:contact"/>
    <file name="jquery.musemenu.js" crc="510910590" ref="index:business:contact"/>
    <file name="jquery.watch.js" crc="51536988" ref="index:business:contact"/>
    <file name="jquery.musepolyfill.bgsize.js" crc="4260645839" ref="index"/>
    <file name="html5shiv.js" crc="4241844378" ref="index:business:contact"/>
    <file name="require.js" crc="7928878" ref="index:business:contact"/>
    <file name="webpro.js" crc="4059564322" ref="business:contact"/>
    <file name="musewpslideshow.js" crc="3862962738" ref="business"/>
    <file name="jquery.museoverlay.js" crc="4147669564" ref="business"/>
    <file name="touchswipe.js" crc="4075097462" ref="business"/>
    <file name="form_check.php" crc="4020933626" ref="contact"/>
    <file name="form_throttle.php" crc="4259590256" ref="contact"/>
    <file name="form_process.php" crc="37464564" ref="contact"/>
    <file name="form-u1080.php" crc="4126147153" ref="contact"/>
  </folder>
  <folder name="images">
    <file name="profile.jpg" crc="27073585" ref="index">
      <caption webpage="index" alt=""/>
    </file>
    <file name="img568x51.jpg" crc="140059452" seo="true" ref="business">
      <caption webpage="business" alt=""/>
    </file>
    <file name="img768x51.jpg" crc="239098854" seo="true" ref="business">
      <caption webpage="business" alt=""/>
    </file>
    <file name="img9-crop-u1033.jpg" crc="22832538" seo="true" ref="business">
      <caption webpage="business" alt=""/>
    </file>
    <file name="img368x51.jpg" crc="4212783443" seo="true" ref="business">
      <caption webpage="business" alt=""/>
    </file>
    <file name="img668x51.jpg" crc="208422600" seo="true" ref="business">
      <caption webpage="business" alt=""/>
    </file>
    <file name="img168x51.jpg" crc="3768523348" seo="true" ref="business">
      <caption webpage="business" alt=""/>
    </file>
    <file name="img868x51.jpg" crc="271595788" seo="true" ref="business">
      <caption webpage="business" alt=""/>
    </file>
    <file name="img268x51.jpg" crc="4071557" seo="true" ref="business">
      <caption webpage="business" alt=""/>
    </file>
    <file name="img4-crop-u938.jpg" crc="492014346" seo="true" ref="business">
      <caption webpage="business" alt=""/>
    </file>
    <file name="img5.jpg" crc="422163169" seo="true" ref="business">
      <caption webpage="business" alt=""/>
    </file>
    <file name="blank.gif" crc="4208392903" ref="business"/>
    <file name="img1.jpg" crc="155871449" seo="true" ref="business">
      <caption webpage="business" alt=""/>
    </file>
    <file name="img7.jpg" crc="4148719902" seo="true" ref="business">
      <caption webpage="business" alt=""/>
    </file>
    <file name="img8.jpg" crc="80785915" seo="true" ref="business">
      <caption webpage="business" alt=""/>
    </file>
    <file name="img9-crop-u1027.jpg" crc="4039535730" seo="true" ref="business">
      <caption webpage="business" alt=""/>
    </file>
    <file name="img2.jpg" crc="267746510" seo="true" ref="business">
      <caption webpage="business" alt=""/>
    </file>
    <file name="img3.jpg" crc="3770918864" seo="true" ref="business">
      <caption webpage="business" alt=""/>
    </file>
    <file name="img4-crop-u932.jpg" crc="4089536749" seo="true" ref="business">
      <caption webpage="business" alt=""/>
    </file>
    <file name="img6.jpg" crc="347691756" seo="true" ref="business">
      <caption webpage="business" alt=""/>
    </file>
    <file name="loading.gif" crc="3815509949" ref="business"/>
  </folder>
  <file name="index.html" crc="370748885" seo="true" mt="1542684070690" redirect="true"/>
  <file name="business.html" crc="4101784431" seo="true" mt="1542684070690" redirect="true"/>
  <file name="contact.html" crc="4085153294" seo="true" mt="1542684070690" redirect="true"/>
</manifest>